setup.py
distributions_DtoE/Binomialdistribution.py
distributions_DtoE/Gaussiandistribution.py
distributions_DtoE/Generaldistribution.py
distributions_DtoE/__init__.py
distributions_DtoE.egg-info/PKG-INFO
distributions_DtoE.egg-info/SOURCES.txt
distributions_DtoE.egg-info/dependency_links.txt
distributions_DtoE.egg-info/not-zip-safe
distributions_DtoE.egg-info/top_level.txt