Metadata-Version: 1.0
Name: distributions-DtoE
Version: 0.1
Summary: Gaussian distributions
Home-page: UNKNOWN
Author: ReneeJia
Author-email: rj368@cornell.edu
License: UNKNOWN
Platform: UNKNOWN
